{
  "collapse-filter": false,
  "search": "",
  "showTags": false,
  "showAttachments": false,
  "hideUnresolved": false,
  "showOrphans": true,
  "collapse-color-groups": false,
  "colorGroups": [
    {
      "query": "#работа_с_файлами",
      "color": {
        "a": 1,
        "rgb": 12189486
      }
    },
    {
      "query": "#итерируемый_объект",
      "color": {
        "a": 1,
        "rgb": 13311
      }
    },
    {
      "query": "#неизменяемый_объект",
      "color": {
        "a": 1,
        "rgb": 16732754
      }
    },
    {
      "query": "#изменяемый_объект",
      "color": {
        "a": 1,
        "rgb": 165120
      }
    },
    {
      "query": "#встроенная_функция",
      "color": {
        "a": 1,
        "rgb": 16059062
      }
    },
    {
      "query": "#модуль",
      "color": {
        "a": 1,
        "rgb": 6081023
      }
    },
    {
      "query": "#метод",
      "color": {
        "a": 1,
        "rgb": 11206906
      }
    },
    {
      "query": "#механика",
      "color": {
        "a": 1,
        "rgb": 16766208
      }
    },
    {
      "query": "#Linux",
      "color": {
        "a": 1,
        "rgb": 49151
      }
    },
    {
      "query": "#исключения",
      "color": {
        "a": 1,
        "rgb": 16711680
      }
    },
    {
      "query": "#Рекурсия",
      "color": {
        "a": 1,
        "rgb": 16755200
      }
    },
    {
      "query": "#функция",
      "color": {
        "a": 1,
        "rgb": 61183
      }
    },
    {
      "query": "#магический_метод",
      "color": {
        "a": 1,
        "rgb": 14966015
      }
    },
    {
      "query": "#OOP",
      "color": {
        "a": 1,
        "rgb": 5431473
      }
    },
    {
      "query": "#docker",
      "color": {
        "a": 1,
        "rgb": 5419488
      }
    },
    {
      "query": "#СУБД",
      "color": {
        "a": 1,
        "rgb": 25343
      }
    },
    {
      "query": "#http",
      "color": {
        "a": 1,
        "rgb": 16711791
      }
    },
    {
      "query": "#API",
      "color": {
        "a": 1,
        "rgb": 5395121
      }
    },
    {
      "query": "#python",
      "color": {
        "a": 1,
        "rgb": 16771584
      }
    },
    {
      "query": "#FastAPI",
      "color": {
        "a": 1,
        "rgb": 65505
      }
    }
  ],
  "collapse-display": false,
  "showArrow": false,
  "textFadeMultiplier": -3,
  "nodeSizeMultiplier": 1.73333333333333,
  "lineSizeMultiplier": 1.88645833333333,
  "collapse-forces": true,
  "centerStrength": 0.307291666666667,
  "repelStrength": 20,
  "linkStrength": 1,
  "linkDistance": 387,
  "scale": 0.08317427835927724,
  "close": false
}